snapcastcontrol/__init__.py
snapcastcontrol/control/SnapControl.py
snapcastcontrol/control/__init__.py
snapcastcontrol/control/library/Actions.py
snapcastcontrol/control/library/Client.py
snapcastcontrol/control/library/Group.py
snapcastcontrol/control/library/Host.py
snapcastcontrol/control/library/Server.py
snapcastcontrol/control/library/SnapControlProtocol.py
snapcastcontrol/control/library/Stream.py
snapcastcontrol/control/library/__init__.py
snapcastcontrol-0.1.0.dist-info/LICENSE
snapcastcontrol-0.1.0.dist-info/WHEEL
snapcastcontrol-0.1.0.dist-info/METADATA
snapcastcontrol-0.1.0.dist-info/RECORD
