Metadata-Version: 2.1
Name: snapcastcontrol
Version: 0.1.0
Summary: snapcastcontrol
Home-page: https://github.com/poulsp/python-snapcastcontrol
Author: Poul Spang
Requires-Python: >=3.7
Classifier: License :: OSI Approved :: GNU General Public License v3 or later (GPLv3+)
Classifier: Programming Language :: Python :: 3
